{
  "type": "minecraft:crafting_shaped",
  "pattern": [
    " 1 ",
    "345",
    "678"
  ],
  "key": {
    "1": {
      "item": "minecraft:spruce_leaves"
    },
    "3": {
      "item": "minecraft:mossy_cobblestone"
    },
    "4": {
      "item": "minecraft:spruce_sapling"
    },
    "5": {
      "item": "minecraft:mossy_cobblestone"
    },
    "6": {
      "item": "minecraft:podzol"
    },
    "7": {
      "item": "minecraft:podzol"
    },
    "8": {
      "item": "minecraft:podzol"
    }
  },
  "result": {
    "item": "elementure:taigamemorial",
    "count": 1
  }
}