{
  "_fv": 39,
  "_type": "recipe",
  "definition": {
    "recipeType": "Crafting",
    "xpReward": 0.0,
    "cookingTime": 200,
    "recipeRetstackSize": 1,
    "recipeShapeless": false,
    "recipeSlots": [
      {
        "value": "CUSTOM:Silveringot"
      },
      {
        "value": "Items.QUARTZ"
      },
      {
        "value": "CUSTOM:Silveringot"
      },
      {
        "value": "CUSTOM:Elementalweb"
      },
      {
        "value": "Blocks.GLASS"
      },
      {
        "value": "CUSTOM:Elementalweb"
      },
      {
        "value": "CUSTOM:Silveringot"
      },
      {
        "value": "Items.QUARTZ"
      },
      {
        "value": "CUSTOM:Silveringot"
      }
    ],
    "recipeReturnStack": {
      "value": "CUSTOM:Silvercore"
    },
    "smeltingInputStack": {
      "value": ""
    },
    "smeltingReturnStack": {
      "value": ""
    },
    "name": "silvercorerecipe",
    "namespace": "mod"
  }
}